{"webrtc__index.md":"0378f936","base_browser__index.md":"ddb2fb9f","base_css_001.md":"bbffcbaa","base_css_002.md":"7ae5abb2","base_css_003.md":"754a624e","base_css_index.md":"1d979d5a","base_http__index.md":"7376936b","base_js_001.md":"a1ff6384","base_js_002.md":"6eff67d9","base_js_index.md":"7c1a5c5a","base_react_001.md":"095b6912","base_react_index.md":"f3f98d44","base_vue_001.md":"4401893f","base_vue_index.md":"0b2fd07d","build_babel_001.md":"e1e405c2","build_babel_index.md":"d14d7d05","build_rollup__index.md":"22b72af3","build_vite__index.md":"0b302102","build_webpack__index.md":"c364bdbc","forward_001.md":"33eb7bd1","forward_002.md":"42f08f69","forward_003.md":"6e88fd50","forward_004.md":"333ea57b","forward_005.md":"31e13657","forward_006.md":"c37cf506","forward_007.md":"97019811","forward_008.md":"7793c11f","forward_009.md":"08e0ceb7","forward_010.md":"05c8ec77","forward_index.md":"ec5654a5","imaging_001.md":"65dec5f3","imaging_index.md":"6819315a","index.md":"6324107f"}
